autopool/__init__.py
autopool/keras.py
autopool/tf.py
autopool/version.py
autopool-0.2.0.dist-info/LICENSE.md
autopool-0.2.0.dist-info/METADATA
autopool-0.2.0.dist-info/WHEEL
autopool-0.2.0.dist-info/top_level.txt
autopool-0.2.0.dist-info/RECORD
