Metadata-Version: 2.1
Name: autopool
Version: 0.2.0
Summary: Adaptive pooling operators for multiple instance learning
Home-page: https://github.com/marl/autopool
Author: MARL
Author-email: brian.mcfee@nyu.edu
License: ISC
Project-URL: Source, https://github.com/marl/autopool
Project-URL: Download, https://github.com/marl/autopool/releases
Platform: UNKNOWN
Classifier: License :: OSI Approved :: MIT License
Classifier: Programming Language :: Python
Classifier: Development Status :: 3 - Alpha
Classifier: Intended Audience :: Developers
Classifier: Topic :: Software Development
Classifier: Programming Language :: Python :: 3
Classifier: Programming Language :: Python :: 3.6
Classifier: Programming Language :: Python :: 3.7
Classifier: Programming Language :: Python :: 3.8
Classifier: Programming Language :: Python :: 3.9
Requires-Python: >=3.6
License-File: LICENSE.md
Provides-Extra: all
Requires-Dist: keras (>=2.2) ; extra == 'all'
Requires-Dist: tensorflow (>=2.0) ; extra == 'all'
Provides-Extra: docs
Requires-Dist: numpydoc ; extra == 'docs'
Requires-Dist: sphinx ; extra == 'docs'
Requires-Dist: sphinx-gallery ; extra == 'docs'
Provides-Extra: keras
Requires-Dist: keras (>=2.2) ; extra == 'keras'
Provides-Extra: tests
Requires-Dist: pytest ; extra == 'tests'
Requires-Dist: pytest-cov ; extra == 'tests'
Requires-Dist: keras (>=2.2) ; extra == 'tests'
Requires-Dist: tensorflow (>=2.0) ; extra == 'tests'
Provides-Extra: tf
Requires-Dist: tensorflow (>=2.0) ; extra == 'tf'
